{
    "author": "Carl Zeiss GOM Metrology GmbH",
    "description": "A simple example showing the usage of script resources.",
    "labels": [],
    "licensing": {
        "licenses": [],
        "product-codes": []
    },
    "references": [
        ["HowTo", "https://zeissiqs.github.io/zeiss-inspect-addon-api/2025/howtos/python_api_introduction/using_script_resources.html"], 
        ["API", "https://zeissiqs.github.io/zeiss-inspect-addon-api/2025/python_api/resource_api.html"]
    ],
    "software-revision": "0000",
    "software-version": "ZEISS INSPECT 2023",
    "tags": [
        "resources"
    ],
    "title": "ScriptResources",
    "uuid": "ffb0632f-850c-418b-a44a-2fa3b0187b78",
    "version": "1.0.1",
    "technical-category": "App Examples",
    "business-category": "minor",
    "compatible-software": ["ZEISS INSPECT Optical 3D", "ZEISS INSPECT X-Ray", "ZEISS INSPECT CMM", "ZEISS INSPECT VMM", "ZEISS CORRELATE"]
}